{
  "topic_id": 11,
  "main_theme": "Environmental and natural resources enablers and barriers for mitigation at national, international, and subnational levels, including land, water, natural resources, minerals, and climate services",
  "key_concepts": [
    "natural resources",
    "land use",
    "water resources",
    "minerals",
    "climate services"
  ],
  "search_queries": [
    "natural resources climate change mitigation",
    "land use climate mitigation",
    "water resources climate change",
    "mineral resources climate mitigation",
    "climate services natural resources"
  ],
  "papers_found": 0,
  "papers_with_openalex_ids": 0,
  "top_papers": [],
  "all_papers": []
}